src/TCP.py
src/URe.py
src/__init__.py
src/packages/MasterboardPacket.py
src/packages/Package.py
src/packages/RobotModePacket.py
src/packages/__init__.py
ur_interface_yorickbm-0.0.1.dist-info/METADATA
ur_interface_yorickbm-0.0.1.dist-info/WHEEL
ur_interface_yorickbm-0.0.1.dist-info/RECORD
